opy/__init__.py
opy/_version.py
opy/opy.py
opy/opy_config.txt
opy/opy_parser.py
opy/opy_patcher.py
opy/settings.py
opy_distbuilder-0.9.1.1.dist-info/LICENSE
opy_distbuilder-0.9.1.1.dist-info/METADATA
opy_distbuilder-0.9.1.1.dist-info/WHEEL
opy_distbuilder-0.9.1.1.dist-info/top_level.txt
opy_distbuilder-0.9.1.1.dist-info/RECORD
